traffic_light_controller.v
`timescale 1ns / 1ps
//////////////////////////////////////////////////////////////////////////////////
// Company: 
// Engineer: 
// 
// Create Date: 17.05.2025 16:39:12
// Design Name: 
// Module Name: traffic_light_controller
// Project Name: 
// Target Devices: 
// Tool Versions: 
// Description: 
// 
// Dependencies: 
// 
// Revision:
// Revision 0.01 - File Created
// Additional Comments:
// 
//////////////////////////////////////////////////////////////////////////////////


module traffic_light_controller (
    input wire clk,            // Clock input
    input wire rst,            // Synchronous reset
    output reg [2:0] ns_light, // NS light: Green=001, Yellow=010, Red=100
    output reg [2:0] ew_light  // EW light: Green=001, Yellow=010, Red=100
);

    // State encoding using localparams
    localparam NS_GREEN_EW_RED  = 2'b00;
    localparam NS_YELLOW_EW_RED = 2'b01;
    localparam EW_GREEN_NS_RED  = 2'b10;
    localparam EW_YELLOW_NS_RED = 2'b11;

    // Parameters for timing (assuming 1 Hz clock)
    localparam GREEN_TIME  = 6'd30;  // 30 seconds
    localparam YELLOW_TIME = 6'd5;   // 5 seconds

    // Registers
    reg [1:0] current_state, next_state;
    reg [5:0] timer;

    // State and timer update logic
    always @(posedge clk) begin
        if (rst) begin
            current_state <= NS_GREEN_EW_RED;
            timer <= GREEN_TIME;
        end else begin
            if (timer == 0) begin
                current_state <= next_state;
                timer <= (next_state == NS_GREEN_EW_RED || next_state == EW_GREEN_NS_RED) ? GREEN_TIME : YELLOW_TIME;
            end else begin
                timer <= timer - 1;
            end
        end
    end

    // Next state logic
    always @(*) begin
        case (current_state)
            NS_GREEN_EW_RED:   next_state = NS_YELLOW_EW_RED;
            NS_YELLOW_EW_RED:  next_state = EW_GREEN_NS_RED;
            EW_GREEN_NS_RED:   next_state = EW_YELLOW_NS_RED;
            EW_YELLOW_NS_RED:  next_state = NS_GREEN_EW_RED;
            default:           next_state = NS_GREEN_EW_RED;
        endcase
    end

    // Output logic
    always @(*) begin
        case (current_state)
            NS_GREEN_EW_RED: begin
                ns_light = 3'b001; // Green
                ew_light = 3'b100; // Red
            end
            NS_YELLOW_EW_RED: begin
                ns_light = 3'b010; // Yellow
                ew_light = 3'b100; // Red
            end
            EW_GREEN_NS_RED: begin
                ns_light = 3'b100; // Red
                ew_light = 3'b001; // Green
            end
            EW_YELLOW_NS_RED: begin
                ns_light = 3'b100; // Red
                ew_light = 3'b010; // Yellow
            end
            default: begin
                ns_light = 3'b100; // Red
                ew_light = 3'b100; // Red
            end
        endcase
    end

endmodule

traffic_light_tb.v
`timescale 1ns / 1ps
//////////////////////////////////////////////////////////////////////////////////
// Company: 
// Engineer: 
// 
// Create Date: 17.05.2025 16:42:39
// Design Name: 
// Module Name: traffic_light_tb
// Project Name: 
// Target Devices: 
// Tool Versions: 
// Description: 
// 
// Dependencies: 
// 
// Revision:
// Revision 0.01 - File Created
// Additional Comments:
// 
//////////////////////////////////////////////////////////////////////////////////



module traffic_light_tb;

    // Inputs
    reg clk;
    reg rst;

    // Outputs
    wire [2:0] ns_light;
    wire [2:0] ew_light;

    // Instantiate the Unit Under Test (UUT)
    traffic_light_controller uut (
        .clk(clk),
        .rst(rst),
        .ns_light(ns_light),
        .ew_light(ew_light)
    );

    // Clock generation: 1 Hz (1s period)
    initial begin
     $dumpfile("traffic_light.vcd");
        $dumpvars(0, traffic_light_tb);

        clk = 0;
        forever #500000000 clk = ~clk; // Toggle every 0.5s
    end

    // Stimulus
    initial begin
        rst = 1;
        #1000000000; // Hold reset for 1 second
        rst = 0;

        // Simulate for 100 seconds using 1-second steps
        repeat (100) #1000000000;

        $finish;
    end

endmodule

traffic_light.vcd
$date
   Sat May 17 17:11:18 2025
$end

$version
  2023.2
  $dumpfile ("traffic_light.vcd") 
$end

$timescale
  1ps
$end

$scope module traffic_light_tb $end
$var reg 1 ! clk $end
$var reg 1 " rst $end
$var wire 3 # ns_light [2:0] $end
$var wire 3 $ ew_light [2:0] $end
$scope module uut $end
$var wire 1 % clk $end
$var wire 1 & rst $end
$var reg 3 ' ns_light [2:0] $end
$var reg 3 ( ew_light [2:0] $end
$var reg 2 ) current_state [1:0] $end
$var reg 2 * next_state [1:0] $end
$var reg 6 + timer [5:0] $end
$upscope $end
$upscope $end
$enddefinitions $end

#0
$dumpvars
0!
1"
bx #
bx $
0%
1&
bx '
bx (
bx )
bx *
bx +
$end

#500000000000
1!
b1 #
b100 $
1%
b1 '
b100 (
b0 )
b1 *
b11110 +

#1000000000000
0!
0"
0%
0&

#1500000000000
1!
1%
b11101 +

#2000000000000
0!
0%

#2500000000000
1!
1%
b11100 +

#3000000000000
0!
0%

#3500000000000
1!
1%
b11011 +

#4000000000000
0!
0%

#4500000000000
1!
1%
b11010 +

#5000000000000
0!
0%

#5500000000000
1!
1%
b11001 +

#6000000000000
0!
0%

#6500000000000
1!
1%
b11000 +

#7000000000000
0!
0%

#7500000000000
1!
1%
b10111 +

#8000000000000
0!
0%

#8500000000000
1!
1%
b10110 +

#9000000000000
0!
0%

#9500000000000
1!
1%
b10101 +

#10000000000000
0!
0%

#10500000000000
1!
1%
b10100 +

#11000000000000
0!
0%

#11500000000000
1!
1%
b10011 +

#12000000000000
0!
0%

#12500000000000
1!
1%
b10010 +

#13000000000000
0!
0%

#13500000000000
1!
1%
b10001 +

#14000000000000
0!
0%

#14500000000000
1!
1%
b10000 +

#15000000000000
0!
0%

#15500000000000
1!
1%
b1111 +

#16000000000000
0!
0%

#16500000000000
1!
1%
b1110 +

#17000000000000
0!
0%

#17500000000000
1!
1%
b1101 +

#18000000000000
0!
0%

#18500000000000
1!
1%
b1100 +

#19000000000000
0!
0%

#19500000000000
1!
1%
b1011 +

#20000000000000
0!
0%

#20500000000000
1!
1%
b1010 +

#21000000000000
0!
0%

#21500000000000
1!
1%
b1001 +

#22000000000000
0!
0%

#22500000000000
1!
1%
b1000 +

#23000000000000
0!
0%

#23500000000000
1!
1%
b111 +

#24000000000000
0!
0%

#24500000000000
1!
1%
b110 +

#25000000000000
0!
0%

#25500000000000
1!
1%
b101 +

#26000000000000
0!
0%

#26500000000000
1!
1%
b100 +

#27000000000000
0!
0%

#27500000000000
1!
1%
b11 +

#28000000000000
0!
0%

#28500000000000
1!
1%
b10 +

#29000000000000
0!
0%

#29500000000000
1!
1%
b1 +

#30000000000000
0!
0%

#30500000000000
1!
1%
b0 +

#31000000000000
0!
0%

#31500000000000
1!
b10 #
1%
b10 '
b1 )
b10 *
b101 +

#32000000000000
0!
0%

#32500000000000
1!
1%
b100 +

#33000000000000
0!
0%

#33500000000000
1!
1%
b11 +

#34000000000000
0!
0%

#34500000000000
1!
1%
b10 +

#35000000000000
0!
0%

#35500000000000
1!
1%
b1 +

#36000000000000
0!
0%

#36500000000000
1!
1%
b0 +

#37000000000000
0!
0%

#37500000000000
1!
b100 #
b1 $
1%
b100 '
b1 (
b10 )
b11 *
b11110 +

#38000000000000
0!
0%

#38500000000000
1!
1%
b11101 +

#39000000000000
0!
0%

#39500000000000
1!
1%
b11100 +

#40000000000000
0!
0%

#40500000000000
1!
1%
b11011 +

#41000000000000
0!
0%

#41500000000000
1!
1%
b11010 +

#42000000000000
0!
0%

#42500000000000
1!
1%
b11001 +

#43000000000000
0!
0%

#43500000000000
1!
1%
b11000 +

#44000000000000
0!
0%

#44500000000000
1!
1%
b10111 +

#45000000000000
0!
0%

#45500000000000
1!
1%
b10110 +

#46000000000000
0!
0%

#46500000000000
1!
1%
b10101 +

#47000000000000
0!
0%

#47500000000000
1!
1%
b10100 +

#48000000000000
0!
0%

#48500000000000
1!
1%
b10011 +

#49000000000000
0!
0%

#49500000000000
1!
1%
b10010 +

#50000000000000
0!
0%

#50500000000000
1!
1%
b10001 +

#51000000000000
0!
0%

#51500000000000
1!
1%
b10000 +

#52000000000000
0!
0%

#52500000000000
1!
1%
b1111 +

#53000000000000
0!
0%

#53500000000000
1!
1%
b1110 +

#54000000000000
0!
0%

#54500000000000
1!
1%
b1101 +

#55000000000000
0!
0%

#55500000000000
1!
1%
b1100 +

#56000000000000
0!
0%

#56500000000000
1!
1%
b1011 +

#57000000000000
0!
0%

#57500000000000
1!
1%
b1010 +

#58000000000000
0!
0%

#58500000000000
1!
1%
b1001 +

#59000000000000
0!
0%

#59500000000000
1!
1%
b1000 +

#60000000000000
0!
0%

#60500000000000
1!
1%
b111 +

#61000000000000
0!
0%

#61500000000000
1!
1%
b110 +

#62000000000000
0!
0%

#62500000000000
1!
1%
b101 +

#63000000000000
0!
0%

#63500000000000
1!
1%
b100 +

#64000000000000
0!
0%

#64500000000000
1!
1%
b11 +

#65000000000000
0!
0%

#65500000000000
1!
1%
b10 +

#66000000000000
0!
0%

#66500000000000
1!
1%
b1 +

#67000000000000
0!
0%

#67500000000000
1!
1%
b0 +

#68000000000000
0!
0%

#68500000000000
1!
b10 $
1%
b10 (
b11 )
b0 *
b101 +

#69000000000000
0!
0%

#69500000000000
1!
1%
b100 +

#70000000000000
0!
0%

#70500000000000
1!
1%
b11 +

#71000000000000
0!
0%

#71500000000000
1!
1%
b10 +

#72000000000000
0!
0%

#72500000000000
1!
1%
b1 +

#73000000000000
0!
0%

#73500000000000
1!
1%
b0 +

#74000000000000
0!
0%

#74500000000000
1!
b1 #
b100 $
1%
b1 '
b100 (
b0 )
b1 *
b11110 +

#75000000000000
0!
0%

#75500000000000
1!
1%
b11101 +

#76000000000000
0!
0%

#76500000000000
1!
1%
b11100 +

#77000000000000
0!
0%

#77500000000000
1!
1%
b11011 +

#78000000000000
0!
0%

#78500000000000
1!
1%
b11010 +

#79000000000000
0!
0%

#79500000000000
1!
1%
b11001 +

#80000000000000
0!
0%

#80500000000000
1!
1%
b11000 +

#81000000000000
0!
0%

#81500000000000
1!
1%
b10111 +

#82000000000000
0!
0%

#82500000000000
1!
1%
b10110 +

#83000000000000
0!
0%

#83500000000000
1!
1%
b10101 +

#84000000000000
0!
0%

#84500000000000
1!
1%
b10100 +

#85000000000000
0!
0%

#85500000000000
1!
1%
b10011 +

#86000000000000
0!
0%

#86500000000000
1!
1%
b10010 +

#87000000000000
0!
0%

#87500000000000
1!
1%
b10001 +

#88000000000000
0!
0%

#88500000000000
1!
1%
b10000 +

#89000000000000
0!
0%

#89500000000000
1!
1%
b1111 +

#90000000000000
0!
0%

#90500000000000
1!
1%
b1110 +

#91000000000000
0!
0%

#91500000000000
1!
1%
b1101 +

#92000000000000
0!
0%

#92500000000000
1!
1%
b1100 +

#93000000000000
0!
0%

#93500000000000
1!
1%
b1011 +

#94000000000000
0!
0%

#94500000000000
1!
1%
b1010 +

#95000000000000
0!
0%

#95500000000000
1!
1%
b1001 +

#96000000000000
0!
0%

#96500000000000
1!
1%
b1000 +

#97000000000000
0!
0%

#97500000000000
1!
1%
b111 +

#98000000000000
0!
0%

#98500000000000
1!
1%
b110 +

#99000000000000
0!
0%

#99500000000000
1!
1%
b101 +

#100000000000000
0!
0%

#100500000000000
1!
1%
b100 +
